examples/Genetic_algorithm/__init__.py
examples/Genetic_algorithm/TSP/__init__.py
examples/Genetic_algorithm/TSP/_1D/Example_GA_TSP_Vary_Mutation.py
examples/Genetic_algorithm/TSP/_1D/__init__.py
examples/Genetic_algorithm/TSP/_1D/Problems/__init__.py
examples/Genetic_algorithm/TSP/_1D/Problems/ga_tsp_vary_mutation.py
examples/Genetic_algorithm/TSP/_2D/Example_GA_TSP_Vary_Mutation_Population_Size.py
examples/Genetic_algorithm/TSP/_2D/__init__.py
examples/Genetic_algorithm/TSP/_2D/Problems/__init__.py
examples/Genetic_algorithm/TSP/_2D/Problems/ga_tsp_2d.py
examples/Machine_learning/__init__.py
examples/Machine_learning/NeuralNetwork/__init__.py
examples/Machine_learning/NeuralNetwork/Segmentation/UnetExample.py
examples/Machine_learning/NeuralNetwork/Segmentation/__init__.py
examples/Machine_learning/NeuralNetwork/Segmentation/scripts/__init__.py
examples/Machine_learning/NeuralNetwork/Segmentation/scripts/dataset.py
examples/Machine_learning/NeuralNetwork/Segmentation/scripts/metric.py
examples/Machine_learning/NeuralNetwork/Segmentation/scripts/model.py
examples/Machine_learning/SVC/__init__.py
examples/Machine_learning/SVC/_1D/Example_SVC_Fixed_kernel_coefficient.py
examples/Machine_learning/SVC/_1D/Example_SVC_Fixed_regularization.py
examples/Machine_learning/SVC/_1D/__init__.py
examples/Machine_learning/SVC/_1D/Problems/SVC_Fixed_Kernel.py
examples/Machine_learning/SVC/_1D/Problems/SVC_Fixed_Regularization.py
examples/Machine_learning/SVC/_1D/Problems/__init__.py
examples/Machine_learning/SVC/_2D/Example_2D_SVC.py
examples/Machine_learning/SVC/_2D/Example_2D_SVC_Industrial.py
examples/Machine_learning/SVC/_2D/Example_SVC_2D_MCO_Transformators_State.py
examples/Machine_learning/SVC/_2D/Example_SVC_2D_Transformators_State.py
examples/Machine_learning/SVC/_2D/Example_SVC_Float_Discrete.py
examples/Machine_learning/SVC/_2D/MCO_breast_cancer_example.py
examples/Machine_learning/SVC/_2D/__init__.py
iOpt-0.5.0.dist-info/LICENSE
iOpt-0.5.0.dist-info/METADATA
iOpt-0.5.0.dist-info/WHEEL
iOpt-0.5.0.dist-info/top_level.txt
iOpt-0.5.0.dist-info/RECORD
