Metadata-Version: 2.1
Name: iOpt
Version: 0.5.0
Summary: Framework for automatically tuning hyperparameter values for mathematical models, AI and ML.
Home-page: https://github.com/aimclub/iOpt
Author: UNN Team
Author-email: 
Classifier: Programming Language :: Python :: 3
Classifier: License :: OSI Approved :: BSD License
Classifier: Operating System :: OS Independent
Requires-Python: >=3.9
License-File: LICENSE
Requires-Dist: numpy <2.0,>=1.19
Requires-Dist: depq
Requires-Dist: cycler
Requires-Dist: kiwisolver
Requires-Dist: matplotlib >=3.3.2
Requires-Dist: scikit-learn
Requires-Dist: sphinx-rtd-theme
Requires-Dist: readthedocs-sphinx-search
Requires-Dist: sphinxcontrib-details-directive
Requires-Dist: autodocsumm
Requires-Dist: pathos
Requires-Dist: multiprocess
Requires-Dist: dash
Requires-Dist: dash-bootstrap-components
Requires-Dist: plotly
Requires-Dist: pandas
Requires-Dist: scipy
